modem_info/__init__.py
modem_info/__main__.py
modem_info/_version.py
modem_info/get.py
modem_info/plot.py
modem_info/py.typed
modem_info/drivers/__init__.py
modem_info/drivers/utils.py
modem_info/drivers/hitron/__init__.py
modem_info/drivers/hitron/coda45/__init__.py
modem_info/drivers/hitron/coda45/driver.py
modem_info/drivers/hitron/coda45/models.py
modem_info/drivers/hitron/coda45/tests.py
modem_info/drivers/hitron/coda45/test_data/dsinfo.json
modem_info/drivers/hitron/coda45/test_data/dsofdminfo.json
modem_info/drivers/hitron/coda45/test_data/getCMInit.json
modem_info/drivers/hitron/coda45/test_data/getCmDocsisWan.json
modem_info/drivers/hitron/coda45/test_data/getLinkStatus.json
modem_info/drivers/hitron/coda45/test_data/getSysInfo.json
modem_info/drivers/hitron/coda45/test_data/usinfo.json
modem_info/drivers/hitron/coda45/test_data/usofdminfo.json
modem_info-1.0.1.dist-info/licenses/LICENSE
modem_info-1.0.1.dist-info/METADATA
modem_info-1.0.1.dist-info/WHEEL
modem_info-1.0.1.dist-info/entry_points.txt
modem_info-1.0.1.dist-info/top_level.txt
modem_info-1.0.1.dist-info/RECORD
