Metadata-Version: 2.4
Name: modem-info
Version: 1.0.1
Summary: Get detailed information and statistics from your cable modem.
Author-email: Ryan Kozak <ReK42@users.noreply.github.com>
Maintainer-email: Ryan Kozak <ReK42@users.noreply.github.com>
License:                     GNU GENERAL PUBLIC LICENSE
Project-URL: Repository, https://github.com/ReK42/modem-info
Project-URL: Issues, https://github.com/ReK42/modem-info/issues
Keywords: modem,docsis
Classifier: Development Status :: 4 - Beta
Classifier: Environment :: Console
Classifier: Intended Audience :: End Users/Desktop
Classifier: Intended Audience :: Information Technology
Classifier: Intended Audience :: Telecommunications Industry
Classifier: License :: OSI Approved :: GNU General Public License v3 (GPLv3)
Classifier: Natural Language :: English
Classifier: Operating System :: OS Independent
Classifier: Programming Language :: Python
Classifier: Programming Language :: Python :: 3
Classifier: Programming Language :: Python :: 3 :: Only
Classifier: Programming Language :: Python :: 3.10
Classifier: Programming Language :: Python :: 3.11
Classifier: Programming Language :: Python :: 3.12
Classifier: Topic :: System :: Monitoring
Classifier: Topic :: System :: Networking
Classifier: Topic :: System :: Networking :: Monitoring
Classifier: Topic :: Utilities
Classifier: Typing :: Typed
Requires-Python: >=3.10
License-File: LICENSE
Requires-Dist: click==8.2.1
Requires-Dist: httpx==0.28.1
Requires-Dist: rich==14.1.0
Requires-Dist: pydantic==2.11.9
Requires-Dist: pydantic-extra-types==2.10.5
Requires-Dist: pandas==2.3.2
Requires-Dist: plotly==5.23.0
Provides-Extra: test
Requires-Dist: ruff==0.13.0; extra == "test"
Requires-Dist: mypy==1.18.1; extra == "test"
Requires-Dist: pandas-stubs==2.3.2.250827; extra == "test"
Provides-Extra: build
Requires-Dist: setuptools==80.9.0; extra == "build"
Requires-Dist: setuptools-scm==9.2.0; extra == "build"
Requires-Dist: build==1.3.0; extra == "build"
Requires-Dist: twine==6.2.0; extra == "build"
Dynamic: license-file
